eofetch/__init__.py
eofetch/__main__.py
eofetch/cdse.py
eofetch/fetch.py
eofetch/s5ppal.py
eofetch-0.3.dist-info/LICENSE
eofetch-0.3.dist-info/METADATA
eofetch-0.3.dist-info/WHEEL
eofetch-0.3.dist-info/entry_points.txt
eofetch-0.3.dist-info/top_level.txt
eofetch-0.3.dist-info/RECORD
